Metadata-Version: 1.1
Name: nasadap
Version: 1.3.2
Summary: Class and functions for downloading NASA data into xarray
Home-page: https://github.com/mullenkamp/nasadap
Author: Mike Kittridge
Author-email: mullenkamp1@gmail.com
License: Apache
Keywords: nasa data
Platform: UNKNOWN
Classifier: Development Status :: 3 - Alpha
Classifier: Intended Audience :: Developers
Classifier: Topic :: Software Development :: Build Tools
Classifier: License :: OSI Approved :: Apache Software License
Classifier: Programming Language :: Python :: 2
Classifier: Programming Language :: Python :: 2.7
Classifier: Programming Language :: Python :: 3
Classifier: Programming Language :: Python :: 3.4
Classifier: Programming Language :: Python :: 3.5
Classifier: Programming Language :: Python :: 3.6
